pq/__init__.py
pq/api.py
pq/consumer.py
pq/cpubound.py
pq/jobs.py
pq/mq.py
pq/backends/__init__.py
pq/backends/redis.py
pq/server/__init__.py
pq/server/apps.py
pq/server/config.py
pq/server/consumer.py
pq/server/producer.py
pq/server/rpc.py
pq/tasks/__init__.py
pq/tasks/consumer.py
pq/tasks/executor.py
pq/tasks/models.py
pq/tasks/rpc.py
pq/tasks/scheduler.py
pq/tasks/states.py
pq/tasks/task.py
pq/utils/__init__.py
pq/utils/concurrency.py
pq/utils/exc.py
pq/utils/serializers.py
pq/utils/time.py
pq/utils/version.py
pulsar_queue-0.5.2.dist-info/DESCRIPTION.rst
pulsar_queue-0.5.2.dist-info/LICENSE.txt
pulsar_queue-0.5.2.dist-info/METADATA
pulsar_queue-0.5.2.dist-info/RECORD
pulsar_queue-0.5.2.dist-info/WHEEL
pulsar_queue-0.5.2.dist-info/metadata.json
pulsar_queue-0.5.2.dist-info/top_level.txt
