Metadata-Version: 2.0
Name: pulsar-queue
Version: 0.5.2
Summary: Asynchronous task queue
Home-page: https://github.com/quantmind/pulsar-queue
Author: Luca Sbardella
Author-email: luca@quantmind.com
License: BSD
Platform: UNKNOWN
Classifier: Development Status :: 4 - Beta
Classifier: Environment :: Web Environment
Classifier: Intended Audience :: Developers
Classifier: License :: OSI Approved :: BSD License
Classifier: Operating System :: OS Independent
Classifier: Programming Language :: Python
Classifier: Programming Language :: Python :: 3
Classifier: Programming Language :: Python :: 3.5
Classifier: Programming Language :: Python :: 3.6
Classifier: Topic :: Utilities
Requires-Dist: pulsar
Requires-Dist: greenlet
